{
  "niche": "motivation",
  "persona": "motivator_id",
  "character": "avatar_motivator",
  "calendar_entries": 1,
  "script": {
    "hook": "No one tells you this about... morning routine for success",
    "body": "Here's what I learned about morning routine for success...",
    "cta": "Follow for more!",
    "full_text": "No one tells you this about... morning routine for success\n\nHere's what I learned...\n\nFollow for more! \ud83d\udcaa\ud83d\udd25\n\n#motivasi #sukses #semangat #inspirasi",
    "hashtags": [
      "#motivasi",
      "#sukses",
      "#semangat",
      "#inspirasi"
    ]
  },
  "storyboard_scenes": 3,
  "video_path": "/home/openclaw/.openclaw/workspace/skills/1ai-skills/content/content-suite/output/motivation_20260312_194558.mp4",
  "publish_status": {
    "tiktok": {
      "status": "pending",
      "account": "@motivator_id"
    }
  },
  "engagement_status": {
    "plans": [
      {
        "account": "buzzer_02",
        "platform": "tiktok",
        "target": "https://example.com/post1",
        "comment": "tutorial lengkapnya mana?",
        "delay_minutes": 16,
        "scheduled_at": null,
        "status": "pending"
      },
      {
        "account": "buzzer_05",
        "platform": "instagram",
        "target": "https://example.com/post1",
        "comment": "inspiring! \ud83d\ude4c",
        "delay_minutes": 42,
        "scheduled_at": null,
        "status": "pending"
      },
      {
        "account": "buzzer_03",
        "platform": "tiktok",
        "target": "https://example.com/post1",
        "comment": "\ud83d\udd25\ud83d\udd25\ud83d\udd25",
        "delay_minutes": 55,
        "scheduled_at": null,
        "status": "pending"
      }
    ],
    "status": "pending"
  }
}