{
  "facebook": [
    {
      "id": 49674,
      "username": "Lizbeth Anguiano"
    },
    {
      "id": 49611,
      "username": "Belanja"
    },
    {
      "id": 49609,
      "username": "Dewi Shop"
    },
    {
      "id": 49607,
      "username": "Hani Fujiati"
    },
    {
      "id": 49605,
      "username": "Anindira"
    },
    {
      "id": 49603,
      "username": "Bunda Corla"
    },
    {
      "id": 49601,
      "username": "Home 4"
    },
    {
      "id": 48177,
      "username": "Vanezia Herbal"
    },
    {
      "id": 45675,
      "username": "Stevi Shop"
    },
    {
      "id": 45673,
      "username": "Clara Store"
    }
  ],
  "instagram": [
    {
      "id": 49682,
      "username": "favisoraanggraeni"
    },
    {
      "id": 49676,
      "username": "chayangkasih"
    },
    {
      "id": 49661,
      "username": "bkjayautama"
    },
    {
      "id": 49644,
      "username": "riviewprodukcek"
    },
    {
      "id": 49640,
      "username": "ardanardiawan"
    },
    {
      "id": 49634,
      "username": "nyamiresepdapur"
    },
    {
      "id": 49630,
      "username": "ameliacintaimoet"
    },
    {
      "id": 49619,
      "username": "emake.nok"
    },
    {
      "id": 49612,
      "username": "riviewprodukaffiliate"
    },
    {
      "id": 48186,
      "username": "berkahkaryadigitalproduct"
    },
    {
      "id": 47681,
      "username": "berkahkaryadigitalmarketing"
    }
  ],
  "tiktok": [
    {
      "id": 49663,
      "username": "bkjaya00"
    },
    {
      "id": 49659,
      "username": "catatanoperator"
    },
    {
      "id": 49642,
      "username": "sehatseraiphari"
    },
    {
      "id": 48374,
      "username": "riviewprodukfashionjujur"
    },
    {
      "id": 48373,
      "username": "drlifehacks1"
    },
    {
      "id": 48372,
      "username": "divasehatsetiaphari"
    },
    {
      "id": 48338,
      "username": "massehatyuk"
    },
    {
      "id": 48337,
      "username": "nugrohopratama5"
    },
    {
      "id": 48336,
      "username": "baimwongdiskon"
    },
    {
      "id": 48335,
      "username": "clinicguru"
    }
  ],
  "threads": [
    {
      "id": 49683,
      "username": "favisoraanggraeni"
    },
    {
      "id": 49680,
      "username": "berkahkaryadigitalproduct"
    },
    {
      "id": 49677,
      "username": "chayangkasih"
    },
    {
      "id": 49662,
      "username": "bkjayautama"
    },
    {
      "id": 49658,
      "username": "berkahkaryadigitalmarketing"
    },
    {
      "id": 49646,
      "username": "riviewprodukcek"
    },
    {
      "id": 49641,
      "username": "ardanardiawan"
    },
    {
      "id": 49635,
      "username": "nyamiresepdapur"
    },
    {
      "id": 49631,
      "username": "ameliacintaimoet"
    },
    {
      "id": 49618,
      "username": "emake.nok"
    },
    {
      "id": 49614,
      "username": "valdoaffiliate"
    },
    {
      "id": 49613,
      "username": "riviewprodukaffiliate"
    }
  ],
  "youtube": []
}