[
  {
    "id": 49683,
    "platform": "threads",
    "username": "favisoraanggraeni"
  },
  {
    "id": 49682,
    "platform": "instagram",
    "username": "favisoraanggraeni"
  },
  {
    "id": 49680,
    "platform": "threads",
    "username": "berkahkaryadigitalproduct"
  },
  {
    "id": 49678,
    "platform": "youtube",
    "username": "dengan tatapan"
  },
  {
    "id": 49677,
    "platform": "threads",
    "username": "chayangkasih"
  },
  {
    "id": 49676,
    "platform": "instagram",
    "username": "chayangkasih"
  },
  {
    "id": 49675,
    "platform": "facebook",
    "username": "WARZ"
  },
  {
    "id": 49674,
    "platform": "facebook",
    "username": "Lizbeth Anguiano"
  },
  {
    "id": 49673,
    "platform": "facebook",
    "username": "Noticias de actualidad sobre celebridades"
  },
  {
    "id": 49672,
    "platform": "facebook",
    "username": "Mavigadget house"
  },
  {
    "id": 49671,
    "platform": "facebook",
    "username": "Dylan Anderson"
  },
  {
    "id": 49670,
    "platform": "facebook",
    "username": "Mr Degree"
  },
  {
    "id": 49669,
    "platform": "facebook",
    "username": "Su Hao "
  },
  {
    "id": 49668,
    "platform": "facebook",
    "username": "LankyBox"
  },
  {
    "id": 49667,
    "platform": "facebook",
    "username": "MrBeast"
  },
  {
    "id": 49666,
    "platform": "facebook",
    "username": "Cookieswirlc"
  },
  {
    "id": 49665,
    "platform": "facebook",
    "username": "DONA 도나"
  },
  {
    "id": 49664,
    "platform": "facebook",
    "username": "Marta and Rustam"
  },
  {
    "id": 49663,
    "platform": "tiktok",
    "username": "bkjaya00"
  },
  {
    "id": 49662,
    "platform": "threads",
    "username": "bkjayautama"
  },
  {
    "id": 49661,
    "platform": "instagram",
    "username": "bkjayautama"
  },
  {
    "id": 49660,
    "platform": "youtube",
    "username": "berkah karya digital agency"
  },
  {
    "id": 49659,
    "platform": "tiktok",
    "username": "catatanoperator"
  },
  {
    "id": 49658,
    "platform": "threads",
    "username": "berkahkaryadigitalmarketing"
  },
  {
    "id": 49646,
    "platform": "threads",
    "username": "riviewprodukcek"
  },
  {
    "id": 49644,
    "platform": "instagram",
    "username": "riviewprodukcek"
  },
  {
    "id": 49642,
    "platform": "tiktok",
    "username": "sehatseraiphari"
  },
  {
    "id": 49641,
    "platform": "threads",
    "username": "ardanardiawan"
  },
  {
    "id": 49640,
    "platform": "instagram",
    "username": "ardanardiawan"
  },
  {
    "id": 49639,
    "platform": "youtube",
    "username": "BK METAL"
  },
  {
    "id": 49638,
    "platform": "youtube",
    "username": "Mak e Nok"
  },
  {
    "id": 49637,
    "platform": "youtube",
    "username": "Chill Work Zone Lofi"
  },
  {
    "id": 49636,
    "platform": "youtube",
    "username": "Resep Dapur Nyami"
  },
  {
    "id": 49635,
    "platform": "threads",
    "username": "nyamiresepdapur"
  },
  {
    "id": 49634,
    "platform": "instagram",
    "username": "nyamiresepdapur"
  },
  {
    "id": 49633,
    "platform": "facebook",
    "username": "Nyamiresep"
  },
  {
    "id": 49631,
    "platform": "threads",
    "username": "ameliacintaimoet"
  },
  {
    "id": 49630,
    "platform": "instagram",
    "username": "ameliacintaimoet"
  },
  {
    "id": 49619,
    "platform": "instagram",
    "username": "emake.nok"
  },
  {
    "id": 49618,
    "platform": "threads",
    "username": "emake.nok"
  },
  {
    "id": 49617,
    "platform": "linkedin",
    "username": "Andik veris  febriyanto"
  },
  {
    "id": 49614,
    "platform": "threads",
    "username": "valdoaffiliate"
  },
  {
    "id": 49613,
    "platform": "threads",
    "username": "riviewprodukaffiliate"
  },
  {
    "id": 49612,
    "platform": "instagram",
    "username": "riviewprodukaffiliate"
  },
  {
    "id": 49611,
    "platform": "facebook",
    "username": "Belanja"
  },
  {
    "id": 49609,
    "platform": "facebook",
    "username": "Dewi Shop"
  },
  {
    "id": 49607,
    "platform": "facebook",
    "username": "Hani Fujiati"
  },
  {
    "id": 49606,
    "platform": "facebook",
    "username": "Rahapu Developer"
  },
  {
    "id": 49605,
    "platform": "facebook",
    "username": "Anindira"
  },
  {
    "id": 49604,
    "platform": "facebook",
    "username": "Divya Elena"
  },
  {
    "id": 49603,
    "platform": "facebook",
    "username": "Bunda Corla"
  },
  {
    "id": 49602,
    "platform": "facebook",
    "username": "Sunny Aurra"
  },
  {
    "id": 49601,
    "platform": "facebook",
    "username": "Home 4"
  },
  {
    "id": 49600,
    "platform": "facebook",
    "username": "MetDaan Oke"
  },
  {
    "id": 49599,
    "platform": "facebook",
    "username": "Sandraskin"
  },
  {
    "id": 49598,
    "platform": "facebook",
    "username": "Sandraskin fans"
  },
  {
    "id": 48374,
    "platform": "tiktok",
    "username": "riviewprodukfashionjujur"
  },
  {
    "id": 48373,
    "platform": "tiktok",
    "username": "drlifehacks1"
  },
  {
    "id": 48372,
    "platform": "tiktok",
    "username": "divasehatsetiaphari"
  },
  {
    "id": 48338,
    "platform": "tiktok",
    "username": "massehatyuk"
  },
  {
    "id": 48337,
    "platform": "tiktok",
    "username": "nugrohopratama5"
  },
  {
    "id": 48336,
    "platform": "tiktok",
    "username": "baimwongdiskon"
  },
  {
    "id": 48335,
    "platform": "tiktok",
    "username": "clinicguru"
  },
  {
    "id": 48186,
    "platform": "instagram",
    "username": "berkahkaryadigitalproduct"
  },
  {
    "id": 48178,
    "platform": "facebook",
    "username": "Anak cerdas & kreatif"
  },
  {
    "id": 48177,
    "platform": "facebook",
    "username": "Vanezia Herbal"
  },
  {
    "id": 48176,
    "platform": "facebook",
    "username": "Marcello Mastroiani"
  },
  {
    "id": 48175,
    "platform": "facebook",
    "username": "Francesca Inaudi"
  },
  {
    "id": 48174,
    "platform": "facebook",
    "username": "Kiro Ebra"
  },
  {
    "id": 48173,
    "platform": "facebook",
    "username": "Chicas Sexys"
  },
  {
    "id": 48172,
    "platform": "facebook",
    "username": "Sandra skins"
  },
  {
    "id": 48171,
    "platform": "facebook",
    "username": "Sandraskin"
  },
  {
    "id": 48170,
    "platform": "facebook",
    "username": "Big bank challenge"
  },
  {
    "id": 47691,
    "platform": "youtube",
    "username": "grahaelektroniktws"
  },
  {
    "id": 47690,
    "platform": "youtube",
    "username": "Diskon Hunter"
  },
  {
    "id": 47689,
    "platform": "youtube",
    "username": "Mak E Nok"
  },
  {
    "id": 47682,
    "platform": "twitter",
    "username": "AgencyKarya"
  },
  {
    "id": 47681,
    "platform": "instagram",
    "username": "berkahkaryadigitalmarketing"
  },
  {
    "id": 47664,
    "platform": "facebook",
    "username": "Berkah Karya Digital Marketing Agency"
  },
  {
    "id": 45675,
    "platform": "facebook",
    "username": "Stevi Shop"
  },
  {
    "id": 45673,
    "platform": "facebook",
    "username": "Clara Store"
  },
  {
    "id": 45648,
    "platform": "tiktok",
    "username": "jasakontenai"
  },
  {
    "id": 45629,
    "platform": "facebook",
    "username": "Mak E Nok"
  }
]
